setup.py
tag.py
vocabulary.py
mqtag.egg-info/PKG-INFO
mqtag.egg-info/SOURCES.txt
mqtag.egg-info/dependency_links.txt
mqtag.egg-info/entry_points.txt
mqtag.egg-info/requires.txt
mqtag.egg-info/top_level.txt