Metadata-Version: 1.1
Name: mqtag
Version: 0.6.4
Summary: mqtag command
Home-page: https://github.com/meqaio/swagger_meqa
Author: Ying Xie
Author-email: ying@meqa.io
License: MIT
Keywords: swagger REST API testing
Platform: UNKNOWN
Classifier: Development Status :: 3 - Alpha
Classifier: Intended Audience :: Developers
Classifier: Topic :: Software Development :: Testing
Classifier: License :: OSI Approved :: MIT License
Classifier: Programming Language :: Python :: 3
Classifier: Programming Language :: Python :: 3.5
Classifier: Programming Language :: Python :: 3.6
